rs_tabler-0.1.0.dist-info/METADATA
rs_tabler-0.1.0.dist-info/WHEEL
rs_tabler-0.1.0.dist-info/license_files/LICENSE-APACHE
rs_tabler-0.1.0.dist-info/license_files/LICENSE-MIT
tabler/table.pyi
tabler/__init__.py
tabler/tabler.pyi
tabler/utils.py
tabler/settings.pyi
tabler/py.typed
tabler/tabler.abi3.so
rs_tabler-0.1.0.dist-info/RECORD
