Metadata-Version: 2.1
Name: rs-tabler
Version: 0.1.0
Classifier: Programming Language :: Rust
Classifier: Programming Language :: Python :: Implementation :: CPython
Classifier: Programming Language :: Python :: Implementation :: PyPy
License-File: LICENSE-APACHE
License-File: LICENSE-MIT
Keywords: table,text,formatter
Author: Embers-of-the-Fire<stellarishs@163.com>
Author-email: Embers-of-the-Fire<stellarishs@163.com>
License: MIT or Apache-2.0
Requires-Python: >=3.7
